LICENSE
MANIFEST.in
README
setup.cfg
setup.py
LazyEvaluation/__init__.py
lazypy/ForkedFutures.py
lazypy/Functions.py
lazypy/Futures.py
lazypy/LazyClasses.py
lazypy/Promises.py
lazypy/Utils.py
lazypy/__init__.py
lazypy/tests.py
lazypy.egg-info/PKG-INFO
lazypy.egg-info/SOURCES.txt
lazypy.egg-info/dependency_links.txt
lazypy.egg-info/top_level.txt