Metadata-Version: 1.0
Name: lazypy
Version: 0.5
Summary: Lazy Evaluation for Python
Home-page: http://bitbucket.org/rfc1437/lazypy/
Author: Georg Bauer
Author-email: gb@rfc1437.de
License: MIT/X
Platform: BSD
Platform: Linux
Platform: MacOS X
Platform: win32
Classifier: Development Status :: 4 - Beta
Classifier: Intended Audience :: Developers
Classifier: License :: OSI Approved :: BSD License
Classifier: Operating System :: OS Independent
Classifier: Programming Language :: Python
